ipcidrtree/__init__.py
ipcidrtree/iprange.py
ipcidrtree/ipset.py
ipcidrtree-1.3.1.dist-info/LICENSE
ipcidrtree-1.3.1.dist-info/METADATA
ipcidrtree-1.3.1.dist-info/WHEEL
ipcidrtree-1.3.1.dist-info/top_level.txt
ipcidrtree-1.3.1.dist-info/RECORD
